LICENSE
MANIFEST.in
README.rst
setup.py
bootstrap3_datetime_time/__init__.py
bootstrap3_datetime_time/widgets.py
bootstrap3_datetime_time/static/bootstrap3_datetime_time/css/bootstrap-datetimepicker.css
bootstrap3_datetime_time/static/bootstrap3_datetime_time/css/bootstrap-datetimepicker.min.css
bootstrap3_datetime_time/static/bootstrap3_datetime_time/js/bootstrap-datetimepicker_timepicker.js
bootstrap3_datetime_time/static/bootstrap3_datetime_time/js/bootstrap-datetimepicker_timepicker.min.js
bootstrap3_datetime_time/static/bootstrap3_datetime_time/js/moment.min.js
bootstrap3_datetime_time/static/bootstrap3_datetime_time/js/locales/bootstrap-datetimepicker.ar-ma.js
bootstrap3_datetime_time/static/bootstrap3_datetime_time/js/locales/bootstrap-datetimepicker.ar.js
bootstrap3_datetime_time/static/bootstrap3_datetime_time/js/locales/bootstrap-datetimepicker.bg.js
bootstrap3_datetime_time/static/bootstrap3_datetime_time/js/locales/bootstrap-datetimepicker.br.js
bootstrap3_datetime_time/static/bootstrap3_datetime_time/js/locales/bootstrap-datetimepicker.bs.js
bootstrap3_datetime_time/static/bootstrap3_datetime_time/js/locales/bootstrap-datetimepicker.by.js
bootstrap3_datetime_time/static/bootstrap3_datetime_time/js/locales/bootstrap-datetimepicker.ca.js
bootstrap3_datetime_time/static/bootstrap3_datetime_time/js/locales/bootstrap-datetimepicker.cs.js
bootstrap3_datetime_time/static/bootstrap3_datetime_time/js/locales/bootstrap-datetimepicker.cv.js
bootstrap3_datetime_time/static/bootstrap3_datetime_time/js/locales/bootstrap-datetimepicker.da.js
bootstrap3_datetime_time/static/bootstrap3_datetime_time/js/locales/bootstrap-datetimepicker.de.js
bootstrap3_datetime_time/static/bootstrap3_datetime_time/js/locales/bootstrap-datetimepicker.el.js
bootstrap3_datetime_time/static/bootstrap3_datetime_time/js/locales/bootstrap-datetimepicker.en-au.js
bootstrap3_datetime_time/static/bootstrap3_datetime_time/js/locales/bootstrap-datetimepicker.en-ca.js
django_bootstrap3_datetimepicker_timepicker.egg-info/PKG-INFO
django_bootstrap3_datetimepicker_timepicker.egg-info/SOURCES.txt
django_bootstrap3_datetimepicker_timepicker.egg-info/dependency_links.txt
django_bootstrap3_datetimepicker_timepicker.egg-info/top_level.txt